Metadata-Version: 2.1
Name: dropconnect-tensorflow
Version: 0.1.0
Summary: Drop Connect - Tensorflow
Home-page: https://github.com/AryaAftab/dropconnect-tensorflow
Author: Arya Aftab
Author-email: arya.aftab@gmail.com
License: MIT
Keywords: deep learning,tensorflow,drop connect
Platform: UNKNOWN
Classifier: Development Status :: 4 - Beta
Classifier: Intended Audience :: Developers
Classifier: Topic :: Scientific/Engineering :: Artificial Intelligence
Classifier: License :: OSI Approved :: MIT License
Classifier: Programming Language :: Python :: 3.6
License-File: LICENSE
